starmallow/__init__.py
starmallow/applications.py
starmallow/background.py
starmallow/concurrency.py
starmallow/constants.py
starmallow/dataclasses.py
starmallow/datastructures.py
starmallow/decorators.py
starmallow/delimited_field.py
starmallow/docs.py
starmallow/endpoint.py
starmallow/endpoints.py
starmallow/exception_handlers.py
starmallow/exceptions.py
starmallow/fields.py
starmallow/generics.py
starmallow/params.py
starmallow/py.typed
starmallow/request_resolver.py
starmallow/requests.py
starmallow/responses.py
starmallow/routing.py
starmallow/schema_generator.py
starmallow/serializers.py
starmallow/types.py
starmallow/utils.py
starmallow/websockets.py
starmallow/ext/__init__.py
starmallow/ext/marshmallow/__init__.py
starmallow/ext/marshmallow/openapi.py
starmallow/middleware/__init__.py
starmallow/middleware/asyncexitstack.py
starmallow/security/__init__.py
starmallow/security/api_key.py
starmallow/security/base.py
starmallow/security/http.py
starmallow/security/oauth2.py
starmallow/security/open_id_connect_url.py
starmallow/security/utils.py
starmallow-0.9.4.dist-info/METADATA
starmallow-0.9.4.dist-info/WHEEL
starmallow-0.9.4.dist-info/licenses/LICENSE.md
starmallow-0.9.4.dist-info/RECORD
