Metadata-Version: 2.4
Name: starmallow
Version: 0.9.4
Summary: StarMallow framework
Project-URL: Homepage, https://github.com/mvanderlee/starmallow
Author-email: Michiel Vanderlee <jmt.vanderlee@gmail.com>
License-Expression: MIT
License-File: LICENSE.md
Classifier: Development Status :: 3 - Alpha
Classifier: Environment :: Web Environment
Classifier: Framework :: AsyncIO
Classifier: Intended Audience :: Developers
Classifier: Intended Audience :: Information Technology
Classifier: Intended Audience :: System Administrators
Classifier: License :: OSI Approved :: MIT License
Classifier: Operating System :: OS Independent
Classifier: Programming Language :: Python
Classifier: Programming Language :: Python :: 3 :: Only
Classifier: Programming Language :: Python :: 3.11
Classifier: Programming Language :: Python :: 3.12
Classifier: Programming Language :: Python :: 3.13
Classifier: Topic :: Internet
Classifier: Topic :: Internet :: WWW/HTTP
Classifier: Topic :: Internet :: WWW/HTTP :: HTTP Servers
Classifier: Topic :: Software Development
Classifier: Topic :: Software Development :: Libraries
Classifier: Topic :: Software Development :: Libraries :: Application Frameworks
Classifier: Topic :: Software Development :: Libraries :: Python Modules
Classifier: Typing :: Typed
Requires-Python: >=3.11
Requires-Dist: apispec[marshmallow]<7,>=6
Requires-Dist: dpath<3,>=2.1.0
Requires-Dist: marshmallow-dataclass2<9,>=8.8.1
Requires-Dist: marshmallow<4,>=3.18.0
Requires-Dist: python-multipart>=0.0.20
Requires-Dist: pyyaml>=5.4.1
Requires-Dist: starlette>=0.46
Provides-Extra: all
Requires-Dist: orjson; extra == 'all'
Requires-Dist: ujson>=3.2.1; extra == 'all'
Requires-Dist: uvicorn[standard]>=0.12.0; extra == 'all'
Provides-Extra: dev
Requires-Dist: pre-commit>=4; extra == 'dev'
Requires-Dist: ruff==0.11.6; extra == 'dev'
Requires-Dist: uvicorn[standard]>=0.34; extra == 'dev'
Provides-Extra: publish
Requires-Dist: hatch>=1.7.0; extra == 'publish'
Provides-Extra: test
Requires-Dist: coverage[toml]<8.0,>=6.5.0; extra == 'test'
Requires-Dist: httpx>=0.22.0; extra == 'test'
Requires-Dist: mypy<2,>=1.1.1; extra == 'test'
Requires-Dist: pytest>=8; extra == 'test'
Requires-Dist: ruff==0.11.6; extra == 'test'
